quartet_tracelink/__init__.py
quartet_tracelink/apps.py
quartet_tracelink/models.py
quartet_tracelink/urls.py
quartet_tracelink/utils.py
quartet_tracelink/views.py
quartet_tracelink/management/__init__.py
quartet_tracelink/management/commands/__init__.py
quartet_tracelink/management/commands/create_common_attributes_rule.py
quartet_tracelink/management/commands/setup_tracelink.py
quartet_tracelink/management/commands/utils.py
quartet_tracelink/parsing/__init__.py
quartet_tracelink/parsing/epcpyyes.py
quartet_tracelink/parsing/parser.py
quartet_tracelink/static/css/quartet_tr4c3l1nk.css
quartet_tracelink/static/js/quartet_tr4c3l1nk.js
quartet_tracelink/steps/__init__.py
quartet_tracelink/steps/mapping_step.py
quartet_tracelink/steps/output_step.py
quartet_tracelink/steps/steps.py
quartet_tracelink/templates/quartet_tracelink/combined_object_event.xml
quartet_tracelink/templates/quartet_tracelink/common_attributes.xml
quartet_tracelink/templates/quartet_tracelink/disposition_assigned.xml
quartet_tracelink/templates/quartet_tracelink/disposition_assigned_event_extension.xml
quartet_tracelink/templates/quartet_tracelink/disposition_assigned_extended.xml
quartet_tracelink/templates/quartet_tracelink/disposition_assigned_extension.xml
quartet_tracelink/templates/quartet_tracelink/extension.xml
quartet_tracelink/templates/quartet_tracelink/gtin_common_attributes.xml
quartet_tracelink/templates/quartet_tracelink/ilmd.xml
quartet_tracelink/templates/quartet_tracelink/masterdata.xml
quartet_tracelink/templates/quartet_tracelink/masterdata_with_items.xml
quartet_tracelink/templates/quartet_tracelink/number_request.xml
quartet_tracelink/templates/quartet_tracelink/sbdh.xml
quartet_tracelink/templates/quartet_tracelink/shipping_event_extension.xml
quartet_tracelink/templates/quartet_tracelink/shipping_trading_partner.xml
quartet_tracelink/templates/quartet_tracelink/sscc_common_attributes.xml
quartet_tracelink/templates/quartet_tracelink/tracelink_epcis_events_document.xml
quartet_tracelink-3.0.0.dist-info/AUTHORS.rst
quartet_tracelink-3.0.0.dist-info/LICENSE
quartet_tracelink-3.0.0.dist-info/METADATA
quartet_tracelink-3.0.0.dist-info/WHEEL
quartet_tracelink-3.0.0.dist-info/top_level.txt
quartet_tracelink-3.0.0.dist-info/RECORD
