Metadata-Version: 2.1
Name: quartet-tracelink
Version: 3.0.0
Summary: An EPCIS to TraceLink Codec
Home-page: https://gitlab.com/serial-lab/quartet_tracelink
Author: SerialLab Corp
Author-email: slab@serial-lab.com
License: GPLv3
Keywords: quartet_tracelink
Platform: UNKNOWN
Classifier: Development Status :: 5 - Production/Stable
Classifier: Framework :: Django
Classifier: Intended Audience :: Developers
Classifier: License :: OSI Approved :: GNU General Public License v3 (GPLv3)
Classifier: Natural Language :: English
Classifier: Programming Language :: Python :: 3.5
Classifier: Programming Language :: Python :: 3.6
Classifier: Programming Language :: Python :: 3.7
